renutil/__init__.py
renutil/renutil.py
renutil-1.17.0.dist-info/LICENSE
renutil-1.17.0.dist-info/WHEEL
renutil-1.17.0.dist-info/entry_points.txt
renutil-1.17.0.dist-info/METADATA
renutil-1.17.0.dist-info/RECORD
