Metadata-Version: 2.1
Name: renutil
Version: 1.17.0
Summary: A toolkit for managing Ren'Py instances via the command line
Home-page: https://github.com/kobaltcore/renutil
License: MIT
Author: CobaltCore
Author-email: cobaltcore@yandex.com
Requires-Python: >=3.7,<4.0
Classifier: License :: OSI Approved :: MIT License
Classifier: Programming Language :: Python :: 3
Classifier: Programming Language :: Python :: 3.7
Classifier: Programming Language :: Python :: 3.8
Classifier: Programming Language :: Python :: 3.9
Classifier: Programming Language :: Python :: 3.10
Classifier: Programming Language :: Python :: 3.11
Requires-Dist: click (>=8.1.3,<9.0.0)
Requires-Dist: lxml (>=4.8.0,<5.0.0)
Requires-Dist: requests (>=2.27.1,<3.0.0)
Requires-Dist: rich (>=12.4.1,<13.0.0)
Requires-Dist: semantic-version (>=2.9.0,<3.0.0)
Requires-Dist: tqdm (>=4.64.0,<5.0.0)
Project-URL: Repository, https://github.com/kobaltcore/renutil
